nagerapi/__init__.py
nagerapi-0.3.1.dist-info/LICENSE
nagerapi-0.3.1.dist-info/METADATA
nagerapi-0.3.1.dist-info/WHEEL
nagerapi-0.3.1.dist-info/top_level.txt
nagerapi-0.3.1.dist-info/RECORD
