Metadata-Version: 2.1
Name: nagerapi
Version: 0.3.1
Summary: Python wrapper for Nager API https://date.nager.at/Api
Home-page: https://github.com/meisnate12/NagerAPI
Author: Nathan Taggart
Author-email: meisnate12@gmail.com
License: MIT License
Project-URL: Documentation, https://nagerapi.metamanager.wiki
Project-URL: Funding, https://github.com/sponsors/meisnate12
Project-URL: Source, https://github.com/meisnate12/NagerAPI
Project-URL: Issues, https://github.com/meisnate12/NagerAPI/issues
Keywords: nagerapi,nager,wrapper,api
Classifier: Development Status :: 5 - Production/Stable
Classifier: Intended Audience :: Developers
Classifier: Topic :: Software Development :: Libraries
Classifier: Programming Language :: Python
Classifier: Programming Language :: Python :: 3.6
Classifier: Programming Language :: Python :: 3.7
Classifier: Programming Language :: Python :: 3.8
Classifier: Programming Language :: Python :: 3.9
Classifier: Programming Language :: Python :: 3.10
Classifier: Programming Language :: Python :: 3.11
Requires-Python: >=3.6
License-File: LICENSE
Requires-Dist: requests
